{
  "techniques": [
    {
      "name": "",
      "aliases": [],
      "description": "",
      "requirements": "",
      "facets": {
        "authenticatorEmployment": [""],
        "sessionTrustContribution": [""],
        "subjectInteraction": [""],
        "locality": "",
        "factor": "",
        "privacyPreservation": "",
        "revocability": "",
        "contextAwareness": [""],
        "uniqueness": "",
        "directionality": "",
        "subjectType": [""]
      },
      "sources": [],
      "authenticators": []
    }
  ]
}
