{
  "methods": [
    {
      "name": "Carrier Frequency Offset Authentication",
      "aliases": [],
      "description": "Continuous physical layer authentication method based on the unique carrier frequency offset (CFO) of hardware. The method uniquely operates on the physical layer and is intended to be used in conjunction with a classical point-in-time authentication method.",
      "requirements": "Radio hardware",
      "authenticator": {
        "name": "Unique carrier frequency offset characteristics",
        "class": [
          "Possession-based",
          "Hardware"
        ]
      },
      "facets": {
        "sessionTrustContribution": "Continuous-only",
        "interaction": "Passive",
        "locality": "Local",
        "variability": "Static",
        "privacyPreservation": "Onymous",
        "revocability": "Irrevocable",
        "contextAwareness": "Context-unaware",
        "uniqueness": "Unique",
        "directionality": "Unidirectional",
        "subjectType": "Machine"
      },
      "sources": [
        "@article{houPhysicalLayerAuthentication2014a,  title = {Physical {{Layer Authentication}} for {{Mobile Systems}} with {{Time-Varying Carrier Frequency Offsets}}},  author = {Hou, Weikun and Wang, Xianbin and Chouinard, Jean-Yves and Refaey, Ahmed},  year = {2014},  month = may,  journal = {IEEE Transactions on Communications},  volume = {62},  number = {5},  pages = {1658--1667},  issn = {1558-0857},  doi = {10.1109/TCOMM.2014.032914.120921}}"
      ]
    }
  ]
}
